cif2ice/__init__.py
cif2ice/__main__.py
cif2ice/read_cif.py
cif2ice-0.4.1.dist-info/METADATA
cif2ice-0.4.1.dist-info/WHEEL
cif2ice-0.4.1.dist-info/entry_points.txt
cif2ice-0.4.1.dist-info/RECORD
