Metadata-Version: 2.3
Name: cif2ice
Version: 0.4.1
Summary: Prepare ice modules for GenIce from CIF file
License: MIT
Keywords: cif2ice
Author: Masakazu Matsumoto
Author-email: vitroid@gmail.com
Requires-Python: >=3.11,<4.0
Classifier: Development Status :: 4 - Beta
Classifier: Intended Audience :: Developers
Classifier: License :: OSI Approved :: MIT License
Classifier: Programming Language :: Python
Classifier: Programming Language :: Python :: 3
Classifier: Programming Language :: Python :: 3.11
Classifier: Programming Language :: Python :: 3.12
Classifier: Programming Language :: Python :: 3.13
Classifier: Programming Language :: Python :: 3.5
Requires-Dist: jinja2 (>=3.1.6,<4.0.0)
Requires-Dist: numpy
Requires-Dist: pycifrw
Requires-Dist: requests
Requires-Dist: toml (>=0.10.2,<0.11.0)
Requires-Dist: validators
Project-URL: Homepage, https://github.com/vitroid/cif2ice/
Project-URL: Repository, https://github.com/vitroid/cif2ice/
